jfwEncoderDecoder/__init__.py
jfwEncoderDecoder/jfw_common.py
jfwEncoderDecoder/jfw_deserializer.py
jfwEncoderDecoder/jfw_generator.py
jfwEncoderDecoder/jfw_serializer.py
jfwEncoderDecoder/jfw_structs.py
jfwEncoderDecoder-0.2.6.dist-info/LICENSE
jfwEncoderDecoder-0.2.6.dist-info/METADATA
jfwEncoderDecoder-0.2.6.dist-info/WHEEL
jfwEncoderDecoder-0.2.6.dist-info/top_level.txt
jfwEncoderDecoder-0.2.6.dist-info/RECORD
